[
    {
        "url": "https://api.github.com/repos/CyC2018/CS-Notes/pulls/756",
        "id": 302996565,
        "node_id": "MDExOlB1bGxSZXF1ZXN0MzAyOTk2NTY1",
        "html_url": "https://github.com/CyC2018/CS-Notes/pull/756",
        "diff_url": "https://github.com/CyC2018/CS-Notes/pull/756.diff",
        "patch_url": "https://github.com/CyC2018/CS-Notes/pull/756.patch",
        "issue_url": "https://api.github.com/repos/CyC2018/CS-Notes/issues/756",
        "number": 756,
        "state": "open",
        "locked": false,
        "title": "Update Leetcode 题解 - 动态规划.md",
        "user": {
            "login": "gityangge",
            "id": 15266146,
            "node_id": "MDQ6VXNlcjE1MjY2MTQ2",
            "avatar_url": "https://avatars3.githubusercontent.com/u/15266146?v=4",
            "gravatar_id": "",
            "url": "https://api.github.com/users/gityangge",
            "html_url": "https://github.com/gityangge",
            "followers_url": "https://api.github.com/users/gityangge/followers",
            "following_url": "https://api.github.com/users/gityangge/following{/other_user}",
            "gists_url": "https://api.github.com/users/gityangge/gists{/gist_id}",
            "starred_url": "https://api.github.com/users/gityangge/starred{/owner}{/repo}",
            "subscriptions_url": "https://api.github.com/users/gityangge/subscriptions",
            "organizations_url": "https://api.github.com/users/gityangge/orgs",
            "repos_url": "https://api.github.com/users/gityangge/repos",
            "events_url": "https://api.github.com/users/gityangge/events{/privacy}",
            "received_events_url": "https://api.github.com/users/gityangge/received_events",
            "type": "User",
            "site_admin": false
        },
        "body": "i == k，i的信在j中，j的信在i中，应该是交换i j",
        "created_at": "2019-07-31T14:59:33Z",
        "updated_at": "2019-07-31T14:59:33Z",
        "closed_at": null,
        "merged_at": null,
        "merge_commit_sha": "9b02aa374512c90866d965e89cf85358a616cb46",
        "assignee": null,
        "assignees": [],
        "requested_reviewers": [],
        "requested_teams": [],
        "labels": [],
        "milestone": null,
        "commits_url": "https://api.github.com/repos/CyC2018/CS-Notes/pulls/756/commits",
        "review_comments_url": "https://api.github.com/repos/CyC2018/CS-Notes/pulls/756/comments",
        "review_comment_url": "https://api.github.com/repos/CyC2018/CS-Notes/pulls/comments{/number}",
        "comments_url": "https://api.github.com/repos/CyC2018/CS-Notes/issues/756/comments",
        "statuses_url": "https://api.github.com/repos/CyC2018/CS-Notes/statuses/acf58d2c7766063743ee33c24d384b974e79be1f",
        "head": {
            "label": "gityangge:yangge_patch",
            "ref": "yangge_patch",
            "sha": "acf58d2c7766063743ee33c24d384b974e79be1f",
            "user": {
                "login": "gityangge",
                "id": 15266146,
                "node_id": "MDQ6VXNlcjE1MjY2MTQ2",
                "avatar_url": "https://avatars3.githubusercontent.com/u/15266146?v=4",
                "gravatar_id": "",
                "url": "https://api.github.com/users/gityangge",
                "html_url": "https://github.com/gityangge",
                "followers_url": "https://api.github.com/users/gityangge/followers",
                "following_url": "https://api.github.com/users/gityangge/following{/other_user}",
                "gists_url": "https://api.github.com/users/gityangge/gists{/gist_id}",
                "starred_url": "https://api.github.com/users/gityangge/starred{/owner}{/repo}",
                "subscriptions_url": "https://api.github.com/users/gityangge/subscriptions",
                "organizations_url": "https://api.github.com/users/gityangge/orgs",
                "repos_url": "https://api.github.com/users/gityangge/repos",
                "events_url": "https://api.github.com/users/gityangge/events{/privacy}",
                "received_events_url": "https://api.github.com/users/gityangge/received_events",
                "type": "User",
                "site_admin": false
            },
            "repo": {
                "id": 199559998,
                "node_id": "MDEwOlJlcG9zaXRvcnkxOTk1NTk5OTg=",
                "name": "CS-Notes",
                "full_name": "gityangge/CS-Notes",
                "private": false,
                "owner": {
                    "login": "gityangge",
                    "id": 15266146,
                    "node_id": "MDQ6VXNlcjE1MjY2MTQ2",
                    "avatar_url": "https://avatars3.githubusercontent.com/u/15266146?v=4",
                    "gravatar_id": "",
                    "url": "https://api.github.com/users/gityangge",
                    "html_url": "https://github.com/gityangge",
                    "followers_url": "https://api.github.com/users/gityangge/followers",
                    "following_url": "https://api.github.com/users/gityangge/following{/other_user}",
                    "gists_url": "https://api.github.com/users/gityangge/gists{/gist_id}",
                    "starred_url": "https://api.github.com/users/gityangge/starred{/owner}{/repo}",
                    "subscriptions_url": "https://api.github.com/users/gityangge/subscriptions",
                    "organizations_url": "https://api.github.com/users/gityangge/orgs",
                    "repos_url": "https://api.github.com/users/gityangge/repos",
                    "events_url": "https://api.github.com/users/gityangge/events{/privacy}",
                    "received_events_url": "https://api.github.com/users/gityangge/received_events",
                    "type": "User",
                    "site_admin": false
                },
                "html_url": "https://github.com/gityangge/CS-Notes",
                "description": ":books: Tech Interview Guide 技术面试必备基础知识、Leetcode 题解、Java、C++、Python、后端面试、操作系统、计算机网络、系统设计",
                "fork": true,
                "url": "https://api.github.com/repos/gityangge/CS-Notes",
                "forks_url": "https://api.github.com/repos/gityangge/CS-Notes/forks",
                "keys_url": "https://api.github.com/repos/gityangge/CS-Notes/keys{/key_id}",
                "collaborators_url": "https://api.github.com/repos/gityangge/CS-Notes/collaborators{/collaborator}",
                "teams_url": "https://api.github.com/repos/gityangge/CS-Notes/teams",
                "hooks_url": "https://api.github.com/repos/gityangge/CS-Notes/hooks",
                "issue_events_url": "https://api.github.com/repos/gityangge/CS-Notes/issues/events{/number}",
                "events_url": "https://api.github.com/repos/gityangge/CS-Notes/events",
                "assignees_url": "https://api.github.com/repos/gityangge/CS-Notes/assignees{/user}",
                "branches_url": "https://api.github.com/repos/gityangge/CS-Notes/branches{/branch}",
                "tags_url": "https://api.github.com/repos/gityangge/CS-Notes/tags",
                "blobs_url": "https://api.github.com/repos/gityangge/CS-Notes/git/blobs{/sha}",
                "git_tags_url": "https://api.github.com/repos/gityangge/CS-Notes/git/tags{/sha}",
                "git_refs_url": "https://api.github.com/repos/gityangge/CS-Notes/git/refs{/sha}",
                "trees_url": "https://api.github.com/repos/gityangge/CS-Notes/git/trees{/sha}",
                "statuses_url": "https://api.github.com/repos/gityangge/CS-Notes/statuses/{sha}",
                "languages_url": "https://api.github.com/repos/gityangge/CS-Notes/languages",
                "stargazers_url": "https://api.github.com/repos/gityangge/CS-Notes/stargazers",
                "contributors_url": "https://api.github.com/repos/gityangge/CS-Notes/contributors",
                "subscribers_url": "https://api.github.com/repos/gityangge/CS-Notes/subscribers",
                "subscription_url": "https://api.github.com/repos/gityangge/CS-Notes/subscription",
                "commits_url": "https://api.github.com/repos/gityangge/CS-Notes/commits{/sha}",
                "git_commits_url": "https://api.github.com/repos/gityangge/CS-Notes/git/commits{/sha}",
                "comments_url": "https://api.github.com/repos/gityangge/CS-Notes/comments{/number}",
                "issue_comment_url": "https://api.github.com/repos/gityangge/CS-Notes/issues/comments{/number}",
                "contents_url": "https://api.github.com/repos/gityangge/CS-Notes/contents/{+path}",
                "compare_url": "https://api.github.com/repos/gityangge/CS-Notes/compare/{base}...{head}",
                "merges_url": "https://api.github.com/repos/gityangge/CS-Notes/merges",
                "archive_url": "https://api.github.com/repos/gityangge/CS-Notes/{archive_format}{/ref}",
                "downloads_url": "https://api.github.com/repos/gityangge/CS-Notes/downloads",
                "issues_url": "https://api.github.com/repos/gityangge/CS-Notes/issues{/number}",
                "pulls_url": "https://api.github.com/repos/gityangge/CS-Notes/pulls{/number}",
                "milestones_url": "https://api.github.com/repos/gityangge/CS-Notes/milestones{/number}",
                "notifications_url": "https://api.github.com/repos/gityangge/CS-Notes/notifications{?since,all,participating}",
                "labels_url": "https://api.github.com/repos/gityangge/CS-Notes/labels{/name}",
                "releases_url": "https://api.github.com/repos/gityangge/CS-Notes/releases{/id}",
                "deployments_url": "https://api.github.com/repos/gityangge/CS-Notes/deployments",
                "created_at": "2019-07-30T02:31:57Z",
                "updated_at": "2019-07-31T14:57:45Z",
                "pushed_at": "2019-07-31T14:57:38Z",
                "git_url": "git://github.com/gityangge/CS-Notes.git",
                "ssh_url": "git@github.com:gityangge/CS-Notes.git",
                "clone_url": "https://github.com/gityangge/CS-Notes.git",
                "svn_url": "https://github.com/gityangge/CS-Notes",
                "homepage": "https://cyc2018.github.io/CS-Notes",
                "size": 106787,
                "stargazers_count": 0,
                "watchers_count": 0,
                "language": "Java",
                "has_issues": false,
                "has_projects": true,
                "has_downloads": true,
                "has_wiki": true,
                "has_pages": false,
                "forks_count": 0,
                "mirror_url": null,
                "archived": false,
                "disabled": false,
                "open_issues_count": 0,
                "license": null,
                "forks": 0,
                "open_issues": 0,
                "watchers": 0,
                "default_branch": "master"
            }
        },
        "base": {
            "label": "CyC2018:master",
            "ref": "master",
            "sha": "d2a04c48b9978e9dac91f845e0964ba706ae13d0",
            "user": {
                "login": "CyC2018",
                "id": 36260787,
                "node_id": "MDQ6VXNlcjM2MjYwNzg3",
                "avatar_url": "https://avatars3.githubusercontent.com/u/36260787?v=4",
                "gravatar_id": "",
                "url": "https://api.github.com/users/CyC2018",
                "html_url": "https://github.com/CyC2018",
                "followers_url": "https://api.github.com/users/CyC2018/followers",
                "following_url": "https://api.github.com/users/CyC2018/following{/other_user}",
                "gists_url": "https://api.github.com/users/CyC2018/gists{/gist_id}",
                "starred_url": "https://api.github.com/users/CyC2018/starred{/owner}{/repo}",
                "subscriptions_url": "https://api.github.com/users/CyC2018/subscriptions",
                "organizations_url": "https://api.github.com/users/CyC2018/orgs",
                "repos_url": "https://api.github.com/users/CyC2018/repos",
                "events_url": "https://api.github.com/users/CyC2018/events{/privacy}",
                "received_events_url": "https://api.github.com/users/CyC2018/received_events",
                "type": "User",
                "site_admin": false
            },
            "repo": {
                "id": 121395510,
                "node_id": "MDEwOlJlcG9zaXRvcnkxMjEzOTU1MTA=",
                "name": "CS-Notes",
                "full_name": "CyC2018/CS-Notes",
                "private": false,
                "owner": {
                    "login": "CyC2018",
                    "id": 36260787,
                    "node_id": "MDQ6VXNlcjM2MjYwNzg3",
                    "avatar_url": "https://avatars3.githubusercontent.com/u/36260787?v=4",
                    "gravatar_id": "",
                    "url": "https://api.github.com/users/CyC2018",
                    "html_url": "https://github.com/CyC2018",
                    "followers_url": "https://api.github.com/users/CyC2018/followers",
                    "following_url": "https://api.github.com/users/CyC2018/following{/other_user}",
                    "gists_url": "https://api.github.com/users/CyC2018/gists{/gist_id}",
                    "starred_url": "https://api.github.com/users/CyC2018/starred{/owner}{/repo}",
                    "subscriptions_url": "https://api.github.com/users/CyC2018/subscriptions",
                    "organizations_url": "https://api.github.com/users/CyC2018/orgs",
                    "repos_url": "https://api.github.com/users/CyC2018/repos",
                    "events_url": "https://api.github.com/users/CyC2018/events{/privacy}",
                    "received_events_url": "https://api.github.com/users/CyC2018/received_events",
                    "type": "User",
                    "site_admin": false
                },
                "html_url": "https://github.com/CyC2018/CS-Notes",
                "description": ":books: Tech Interview Guide 技术面试必备基础知识、Leetcode 题解、Java、C++、Python、后端面试、操作系统、计算机网络、系统设计",
                "fork": false,
                "url": "https://api.github.com/repos/CyC2018/CS-Notes",
                "forks_url": "https://api.github.com/repos/CyC2018/CS-Notes/forks",
                "keys_url": "https://api.github.com/repos/CyC2018/CS-Notes/keys{/key_id}",
                "collaborators_url": "https://api.github.com/repos/CyC2018/CS-Notes/collaborators{/collaborator}",
                "teams_url": "https://api.github.com/repos/CyC2018/CS-Notes/teams",
                "hooks_url": "https://api.github.com/repos/CyC2018/CS-Notes/hooks",
                "issue_events_url": "https://api.github.com/repos/CyC2018/CS-Notes/issues/events{/number}",
                "events_url": "https://api.github.com/repos/CyC2018/CS-Notes/events",
                "assignees_url": "https://api.github.com/repos/CyC2018/CS-Notes/assignees{/user}",
                "branches_url": "https://api.github.com/repos/CyC2018/CS-Notes/branches{/branch}",
                "tags_url": "https://api.github.com/repos/CyC2018/CS-Notes/tags",
                "blobs_url": "https://api.github.com/repos/CyC2018/CS-Notes/git/blobs{/sha}",
                "git_tags_url": "https://api.github.com/repos/CyC2018/CS-Notes/git/tags{/sha}",
                "git_refs_url": "https://api.github.com/repos/CyC2018/CS-Notes/git/refs{/sha}",
                "trees_url": "https://api.github.com/repos/CyC2018/CS-Notes/git/trees{/sha}",
                "statuses_url": "https://api.github.com/repos/CyC2018/CS-Notes/statuses/{sha}",
                "languages_url": "https://api.github.com/repos/CyC2018/CS-Notes/languages",
                "stargazers_url": "https://api.github.com/repos/CyC2018/CS-Notes/stargazers",
                "contributors_url": "https://api.github.com/repos/CyC2018/CS-Notes/contributors",
                "subscribers_url": "https://api.github.com/repos/CyC2018/CS-Notes/subscribers",
                "subscription_url": "https://api.github.com/repos/CyC2018/CS-Notes/subscription",
                "commits_url": "https://api.github.com/repos/CyC2018/CS-Notes/commits{/sha}",
                "git_commits_url": "https://api.github.com/repos/CyC2018/CS-Notes/git/commits{/sha}",
                "comments_url": "https://api.github.com/repos/CyC2018/CS-Notes/comments{/number}",
                "issue_comment_url": "https://api.github.com/repos/CyC2018/CS-Notes/issues/comments{/number}",
                "contents_url": "https://api.github.com/repos/CyC2018/CS-Notes/contents/{+path}",
                "compare_url": "https://api.github.com/repos/CyC2018/CS-Notes/compare/{base}...{head}",
                "merges_url": "https://api.github.com/repos/CyC2018/CS-Notes/merges",
                "archive_url": "https://api.github.com/repos/CyC2018/CS-Notes/{archive_format}{/ref}",
                "downloads_url": "https://api.github.com/repos/CyC2018/CS-Notes/downloads",
                "issues_url": "https://api.github.com/repos/CyC2018/CS-Notes/issues{/number}",
                "pulls_url": "https://api.github.com/repos/CyC2018/CS-Notes/pulls{/number}",
                "milestones_url": "https://api.github.com/repos/CyC2018/CS-Notes/milestones{/number}",
                "notifications_url": "https://api.github.com/repos/CyC2018/CS-Notes/notifications{?since,all,participating}",
                "labels_url": "https://api.github.com/repos/CyC2018/CS-Notes/labels{/name}",
                "releases_url": "https://api.github.com/repos/CyC2018/CS-Notes/releases{/id}",
                "deployments_url": "https://api.github.com/repos/CyC2018/CS-Notes/deployments",
                "created_at": "2018-02-13T14:56:24Z",
                "updated_at": "2019-08-11T17:16:23Z",
                "pushed_at": "2019-08-11T15:23:32Z",
                "git_url": "git://github.com/CyC2018/CS-Notes.git",
                "ssh_url": "git@github.com:CyC2018/CS-Notes.git",
                "clone_url": "https://github.com/CyC2018/CS-Notes.git",
                "svn_url": "https://github.com/CyC2018/CS-Notes",
                "homepage": "https://cyc2018.github.io/CS-Notes",
                "size": 106799,
                "stargazers_count": 73985,
                "watchers_count": 73985,
                "language": "Java",
                "has_issues": true,
                "has_projects": true,
                "has_downloads": true,
                "has_wiki": true,
                "has_pages": true,
                "forks_count": 23389,
                "mirror_url": null,
                "archived": false,
                "disabled": false,
                "open_issues_count": 16,
                "license": null,
                "forks": 23389,
                "open_issues": 16,
                "watchers": 73985,
                "default_branch": "master"
            }
        },
        "_links": {
            "self": {
                "href": "https://api.github.com/repos/CyC2018/CS-Notes/pulls/756"
            },
            "html": {
                "href": "https://github.com/CyC2018/CS-Notes/pull/756"
            },
            "issue": {
                "href": "https://api.github.com/repos/CyC2018/CS-Notes/issues/756"
            },
            "comments": {
                "href": "https://api.github.com/repos/CyC2018/CS-Notes/issues/756/comments"
            },
            "review_comments": {
                "href": "https://api.github.com/repos/CyC2018/CS-Notes/pulls/756/comments"
            },
            "review_comment": {
                "href": "https://api.github.com/repos/CyC2018/CS-Notes/pulls/comments{/number}"
            },
            "commits": {
                "href": "https://api.github.com/repos/CyC2018/CS-Notes/pulls/756/commits"
            },
            "statuses": {
                "href": "https://api.github.com/repos/CyC2018/CS-Notes/statuses/acf58d2c7766063743ee33c24d384b974e79be1f"
            }
        },
        "author_association": "NONE"
    },
    {
        "url": "https://api.github.com/repos/CyC2018/CS-Notes/pulls/752",
        "id": 300944246,
        "node_id": "MDExOlB1bGxSZXF1ZXN0MzAwOTQ0MjQ2",
        "html_url": "https://github.com/CyC2018/CS-Notes/pull/752",
        "diff_url": "https://github.com/CyC2018/CS-Notes/pull/752.diff",
        "patch_url": "https://github.com/CyC2018/CS-Notes/pull/752.patch",
        "issue_url": "https://api.github.com/repos/CyC2018/CS-Notes/issues/752",
        "number": 752,
        "state": "open",
        "locked": false,
        "title": "修改leetcode题解动态规划01背包问题第五题",
        "user": {
            "login": "gb145234",
            "id": 37872544,
            "node_id": "MDQ6VXNlcjM3ODcyNTQ0",
            "avatar_url": "https://avatars2.githubusercontent.com/u/37872544?v=4",
            "gravatar_id": "",
            "url": "https://api.github.com/users/gb145234",
            "html_url": "https://github.com/gb145234",
            "followers_url": "https://api.github.com/users/gb145234/followers",
            "following_url": "https://api.github.com/users/gb145234/following{/other_user}",
            "gists_url": "https://api.github.com/users/gb145234/gists{/gist_id}",
            "starred_url": "https://api.github.com/users/gb145234/starred{/owner}{/repo}",
            "subscriptions_url": "https://api.github.com/users/gb145234/subscriptions",
            "organizations_url": "https://api.github.com/users/gb145234/orgs",
            "repos_url": "https://api.github.com/users/gb145234/repos",
            "events_url": "https://api.github.com/users/gb145234/events{/privacy}",
            "received_events_url": "https://api.github.com/users/gb145234/received_events",
            "type": "User",
            "site_admin": false
        },
        "body": "当amount为0并且coins数组长度为0时，返回的应该是1，不然leetcode通不过",
        "created_at": "2019-07-25T00:58:11Z",
        "updated_at": "2019-07-25T00:58:11Z",
        "closed_at": null,
        "merged_at": null,
        "merge_commit_sha": "ee566d869d1244ac52a9bcae63e719e0406a56c3",
        "assignee": null,
        "assignees": [],
        "requested_reviewers": [],
        "requested_teams": [],
        "labels": [],
        "milestone": null,
        "commits_url": "https://api.github.com/repos/CyC2018/CS-Notes/pulls/752/commits",
        "review_comments_url": "https://api.github.com/repos/CyC2018/CS-Notes/pulls/752/comments",
        "review_comment_url": "https://api.github.com/repos/CyC2018/CS-Notes/pulls/comments{/number}",
        "comments_url": "https://api.github.com/repos/CyC2018/CS-Notes/issues/752/comments",
        "statuses_url": "https://api.github.com/repos/CyC2018/CS-Notes/statuses/aa0bb2f210a27a9c5aac0b7bfee8aeb86a690e0b",
        "head": {
            "label": "gb145234:work",
            "ref": "work",
            "sha": "aa0bb2f210a27a9c5aac0b7bfee8aeb86a690e0b",
            "user": {
                "login": "gb145234",
                "id": 37872544,
                "node_id": "MDQ6VXNlcjM3ODcyNTQ0",
                "avatar_url": "https://avatars2.githubusercontent.com/u/37872544?v=4",
                "gravatar_id": "",
                "url": "https://api.github.com/users/gb145234",
                "html_url": "https://github.com/gb145234",
                "followers_url": "https://api.github.com/users/gb145234/followers",
                "following_url": "https://api.github.com/users/gb145234/following{/other_user}",
                "gists_url": "https://api.github.com/users/gb145234/gists{/gist_id}",
                "starred_url": "https://api.github.com/users/gb145234/starred{/owner}{/repo}",
                "subscriptions_url": "https://api.github.com/users/gb145234/subscriptions",
                "organizations_url": "https://api.github.com/users/gb145234/orgs",
                "repos_url": "https://api.github.com/users/gb145234/repos",
                "events_url": "https://api.github.com/users/gb145234/events{/privacy}",
                "received_events_url": "https://api.github.com/users/gb145234/received_events",
                "type": "User",
                "site_admin": false
            },
            "repo": {
                "id": 198680161,
                "node_id": "MDEwOlJlcG9zaXRvcnkxOTg2ODAxNjE=",
                "name": "CS-Notes",
                "full_name": "gb145234/CS-Notes",
                "private": false,
                "owner": {
                    "login": "gb145234",
                    "id": 37872544,
                    "node_id": "MDQ6VXNlcjM3ODcyNTQ0",
                    "avatar_url": "https://avatars2.githubusercontent.com/u/37872544?v=4",
                    "gravatar_id": "",
                    "url": "https://api.github.com/users/gb145234",
                    "html_url": "https://github.com/gb145234",
                    "followers_url": "https://api.github.com/users/gb145234/followers",
                    "following_url": "https://api.github.com/users/gb145234/following{/other_user}",
                    "gists_url": "https://api.github.com/users/gb145234/gists{/gist_id}",
                    "starred_url": "https://api.github.com/users/gb145234/starred{/owner}{/repo}",
                    "subscriptions_url": "https://api.github.com/users/gb145234/subscriptions",
                    "organizations_url": "https://api.github.com/users/gb145234/orgs",
                    "repos_url": "https://api.github.com/users/gb145234/repos",
                    "events_url": "https://api.github.com/users/gb145234/events{/privacy}",
                    "received_events_url": "https://api.github.com/users/gb145234/received_events",
                    "type": "User",
                    "site_admin": false
                },
                "html_url": "https://github.com/gb145234/CS-Notes",
                "description": ":books: Tech Interview Guide 技术面试必备基础知识、Leetcode 题解、Java、C++、Python、后端面试、操作系统、计算机网络、系统设计",
                "fork": true,
                "url": "https://api.github.com/repos/gb145234/CS-Notes",
                "forks_url": "https://api.github.com/repos/gb145234/CS-Notes/forks",
                "keys_url": "https://api.github.com/repos/gb145234/CS-Notes/keys{/key_id}",
                "collaborators_url": "https://api.github.com/repos/gb145234/CS-Notes/collaborators{/collaborator}",
                "teams_url": "https://api.github.com/repos/gb145234/CS-Notes/teams",
                "hooks_url": "https://api.github.com/repos/gb145234/CS-Notes/hooks",
                "issue_events_url": "https://api.github.com/repos/gb145234/CS-Notes/issues/events{/number}",
                "events_url": "https://api.github.com/repos/gb145234/CS-Notes/events",
                "assignees_url": "https://api.github.com/repos/gb145234/CS-Notes/assignees{/user}",
                "branches_url": "https://api.github.com/repos/gb145234/CS-Notes/branches{/branch}",
                "tags_url": "https://api.github.com/repos/gb145234/CS-Notes/tags",
                "blobs_url": "https://api.github.com/repos/gb145234/CS-Notes/git/blobs{/sha}",
                "git_tags_url": "https://api.github.com/repos/gb145234/CS-Notes/git/tags{/sha}",
                "git_refs_url": "https://api.github.com/repos/gb145234/CS-Notes/git/refs{/sha}",
                "trees_url": "https://api.github.com/repos/gb145234/CS-Notes/git/trees{/sha}",
                "statuses_url": "https://api.github.com/repos/gb145234/CS-Notes/statuses/{sha}",
                "languages_url": "https://api.github.com/repos/gb145234/CS-Notes/languages",
                "stargazers_url": "https://api.github.com/repos/gb145234/CS-Notes/stargazers",
                "contributors_url": "https://api.github.com/repos/gb145234/CS-Notes/contributors",
                "subscribers_url": "https://api.github.com/repos/gb145234/CS-Notes/subscribers",
                "subscription_url": "https://api.github.com/repos/gb145234/CS-Notes/subscription",
                "commits_url": "https://api.github.com/repos/gb145234/CS-Notes/commits{/sha}",
                "git_commits_url": "https://api.github.com/repos/gb145234/CS-Notes/git/commits{/sha}",
                "comments_url": "https://api.github.com/repos/gb145234/CS-Notes/comments{/number}",
                "issue_comment_url": "https://api.github.com/repos/gb145234/CS-Notes/issues/comments{/number}",
                "contents_url": "https://api.github.com/repos/gb145234/CS-Notes/contents/{+path}",
                "compare_url": "https://api.github.com/repos/gb145234/CS-Notes/compare/{base}...{head}",
                "merges_url": "https://api.github.com/repos/gb145234/CS-Notes/merges",
                "archive_url": "https://api.github.com/repos/gb145234/CS-Notes/{archive_format}{/ref}",
                "downloads_url": "https://api.github.com/repos/gb145234/CS-Notes/downloads",
                "issues_url": "https://api.github.com/repos/gb145234/CS-Notes/issues{/number}",
                "pulls_url": "https://api.github.com/repos/gb145234/CS-Notes/pulls{/number}",
                "milestones_url": "https://api.github.com/repos/gb145234/CS-Notes/milestones{/number}",
                "notifications_url": "https://api.github.com/repos/gb145234/CS-Notes/notifications{?since,all,participating}",
                "labels_url": "https://api.github.com/repos/gb145234/CS-Notes/labels{/name}",
                "releases_url": "https://api.github.com/repos/gb145234/CS-Notes/releases{/id}",
                "deployments_url": "https://api.github.com/repos/gb145234/CS-Notes/deployments",
                "created_at": "2019-07-24T17:22:47Z",
                "updated_at": "2019-07-24T17:22:52Z",
                "pushed_at": "2019-07-25T00:51:22Z",
                "git_url": "git://github.com/gb145234/CS-Notes.git",
                "ssh_url": "git@github.com:gb145234/CS-Notes.git",
                "clone_url": "https://github.com/gb145234/CS-Notes.git",
                "svn_url": "https://github.com/gb145234/CS-Notes",
                "homepage": "https://cyc2018.github.io/CS-Notes",
                "size": 106769,
                "stargazers_count": 0,
                "watchers_count": 0,
                "language": "Java",
                "has_issues": false,
                "has_projects": true,
                "has_downloads": true,
                "has_wiki": true,
                "has_pages": false,
                "forks_count": 0,
                "mirror_url": null,
                "archived": false,
                "disabled": false,
                "open_issues_count": 0,
                "license": null,
                "forks": 0,
                "open_issues": 0,
                "watchers": 0,
                "default_branch": "master"
            }
        },
        "base": {
            "label": "CyC2018:master",
            "ref": "master",
            "sha": "d2a04c48b9978e9dac91f845e0964ba706ae13d0",
            "user": {
                "login": "CyC2018",
                "id": 36260787,
                "node_id": "MDQ6VXNlcjM2MjYwNzg3",
                "avatar_url": "https://avatars3.githubusercontent.com/u/36260787?v=4",
                "gravatar_id": "",
                "url": "https://api.github.com/users/CyC2018",
                "html_url": "https://github.com/CyC2018",
                "followers_url": "https://api.github.com/users/CyC2018/followers",
                "following_url": "https://api.github.com/users/CyC2018/following{/other_user}",
                "gists_url": "https://api.github.com/users/CyC2018/gists{/gist_id}",
                "starred_url": "https://api.github.com/users/CyC2018/starred{/owner}{/repo}",
                "subscriptions_url": "https://api.github.com/users/CyC2018/subscriptions",
                "organizations_url": "https://api.github.com/users/CyC2018/orgs",
                "repos_url": "https://api.github.com/users/CyC2018/repos",
                "events_url": "https://api.github.com/users/CyC2018/events{/privacy}",
                "received_events_url": "https://api.github.com/users/CyC2018/received_events",
                "type": "User",
                "site_admin": false
            },
            "repo": {
                "id": 121395510,
                "node_id": "MDEwOlJlcG9zaXRvcnkxMjEzOTU1MTA=",
                "name": "CS-Notes",
                "full_name": "CyC2018/CS-Notes",
                "private": false,
                "owner": {
                    "login": "CyC2018",
                    "id": 36260787,
                    "node_id": "MDQ6VXNlcjM2MjYwNzg3",
                    "avatar_url": "https://avatars3.githubusercontent.com/u/36260787?v=4",
                    "gravatar_id": "",
                    "url": "https://api.github.com/users/CyC2018",
                    "html_url": "https://github.com/CyC2018",
                    "followers_url": "https://api.github.com/users/CyC2018/followers",
                    "following_url": "https://api.github.com/users/CyC2018/following{/other_user}",
                    "gists_url": "https://api.github.com/users/CyC2018/gists{/gist_id}",
                    "starred_url": "https://api.github.com/users/CyC2018/starred{/owner}{/repo}",
                    "subscriptions_url": "https://api.github.com/users/CyC2018/subscriptions",
                    "organizations_url": "https://api.github.com/users/CyC2018/orgs",
                    "repos_url": "https://api.github.com/users/CyC2018/repos",
                    "events_url": "https://api.github.com/users/CyC2018/events{/privacy}",
                    "received_events_url": "https://api.github.com/users/CyC2018/received_events",
                    "type": "User",
                    "site_admin": false
                },
                "html_url": "https://github.com/CyC2018/CS-Notes",
                "description": ":books: Tech Interview Guide 技术面试必备基础知识、Leetcode 题解、Java、C++、Python、后端面试、操作系统、计算机网络、系统设计",
                "fork": false,
                "url": "https://api.github.com/repos/CyC2018/CS-Notes",
                "forks_url": "https://api.github.com/repos/CyC2018/CS-Notes/forks",
                "keys_url": "https://api.github.com/repos/CyC2018/CS-Notes/keys{/key_id}",
                "collaborators_url": "https://api.github.com/repos/CyC2018/CS-Notes/collaborators{/collaborator}",
                "teams_url": "https://api.github.com/repos/CyC2018/CS-Notes/teams",
                "hooks_url": "https://api.github.com/repos/CyC2018/CS-Notes/hooks",
                "issue_events_url": "https://api.github.com/repos/CyC2018/CS-Notes/issues/events{/number}",
                "events_url": "https://api.github.com/repos/CyC2018/CS-Notes/events",
                "assignees_url": "https://api.github.com/repos/CyC2018/CS-Notes/assignees{/user}",
                "branches_url": "https://api.github.com/repos/CyC2018/CS-Notes/branches{/branch}",
                "tags_url": "https://api.github.com/repos/CyC2018/CS-Notes/tags",
                "blobs_url": "https://api.github.com/repos/CyC2018/CS-Notes/git/blobs{/sha}",
                "git_tags_url": "https://api.github.com/repos/CyC2018/CS-Notes/git/tags{/sha}",
                "git_refs_url": "https://api.github.com/repos/CyC2018/CS-Notes/git/refs{/sha}",
                "trees_url": "https://api.github.com/repos/CyC2018/CS-Notes/git/trees{/sha}",
                "statuses_url": "https://api.github.com/repos/CyC2018/CS-Notes/statuses/{sha}",
                "languages_url": "https://api.github.com/repos/CyC2018/CS-Notes/languages",
                "stargazers_url": "https://api.github.com/repos/CyC2018/CS-Notes/stargazers",
                "contributors_url": "https://api.github.com/repos/CyC2018/CS-Notes/contributors",
                "subscribers_url": "https://api.github.com/repos/CyC2018/CS-Notes/subscribers",
                "subscription_url": "https://api.github.com/repos/CyC2018/CS-Notes/subscription",
                "commits_url": "https://api.github.com/repos/CyC2018/CS-Notes/commits{/sha}",
                "git_commits_url": "https://api.github.com/repos/CyC2018/CS-Notes/git/commits{/sha}",
                "comments_url": "https://api.github.com/repos/CyC2018/CS-Notes/comments{/number}",
                "issue_comment_url": "https://api.github.com/repos/CyC2018/CS-Notes/issues/comments{/number}",
                "contents_url": "https://api.github.com/repos/CyC2018/CS-Notes/contents/{+path}",
                "compare_url": "https://api.github.com/repos/CyC2018/CS-Notes/compare/{base}...{head}",
                "merges_url": "https://api.github.com/repos/CyC2018/CS-Notes/merges",
                "archive_url": "https://api.github.com/repos/CyC2018/CS-Notes/{archive_format}{/ref}",
                "downloads_url": "https://api.github.com/repos/CyC2018/CS-Notes/downloads",
                "issues_url": "https://api.github.com/repos/CyC2018/CS-Notes/issues{/number}",
                "pulls_url": "https://api.github.com/repos/CyC2018/CS-Notes/pulls{/number}",
                "milestones_url": "https://api.github.com/repos/CyC2018/CS-Notes/milestones{/number}",
                "notifications_url": "https://api.github.com/repos/CyC2018/CS-Notes/notifications{?since,all,participating}",
                "labels_url": "https://api.github.com/repos/CyC2018/CS-Notes/labels{/name}",
                "releases_url": "https://api.github.com/repos/CyC2018/CS-Notes/releases{/id}",
                "deployments_url": "https://api.github.com/repos/CyC2018/CS-Notes/deployments",
                "created_at": "2018-02-13T14:56:24Z",
                "updated_at": "2019-08-11T17:16:23Z",
                "pushed_at": "2019-08-11T15:23:32Z",
                "git_url": "git://github.com/CyC2018/CS-Notes.git",
                "ssh_url": "git@github.com:CyC2018/CS-Notes.git",
                "clone_url": "https://github.com/CyC2018/CS-Notes.git",
                "svn_url": "https://github.com/CyC2018/CS-Notes",
                "homepage": "https://cyc2018.github.io/CS-Notes",
                "size": 106799,
                "stargazers_count": 73985,
                "watchers_count": 73985,
                "language": "Java",
                "has_issues": true,
                "has_projects": true,
                "has_downloads": true,
                "has_wiki": true,
                "has_pages": true,
                "forks_count": 23389,
                "mirror_url": null,
                "archived": false,
                "disabled": false,
                "open_issues_count": 16,
                "license": null,
                "forks": 23389,
                "open_issues": 16,
                "watchers": 73985,
                "default_branch": "master"
            }
        },
        "_links": {
            "self": {
                "href": "https://api.github.com/repos/CyC2018/CS-Notes/pulls/752"
            },
            "html": {
                "href": "https://github.com/CyC2018/CS-Notes/pull/752"
            },
            "issue": {
                "href": "https://api.github.com/repos/CyC2018/CS-Notes/issues/752"
            },
            "comments": {
                "href": "https://api.github.com/repos/CyC2018/CS-Notes/issues/752/comments"
            },
            "review_comments": {
                "href": "https://api.github.com/repos/CyC2018/CS-Notes/pulls/752/comments"
            },
            "review_comment": {
                "href": "https://api.github.com/repos/CyC2018/CS-Notes/pulls/comments{/number}"
            },
            "commits": {
                "href": "https://api.github.com/repos/CyC2018/CS-Notes/pulls/752/commits"
            },
            "statuses": {
                "href": "https://api.github.com/repos/CyC2018/CS-Notes/statuses/aa0bb2f210a27a9c5aac0b7bfee8aeb86a690e0b"
            }
        },
        "author_association": "NONE"
    },
    {
        "url": "https://api.github.com/repos/CyC2018/CS-Notes/pulls/745",
        "id": 297023661,
        "node_id": "MDExOlB1bGxSZXF1ZXN0Mjk3MDIzNjYx",
        "html_url": "https://github.com/CyC2018/CS-Notes/pull/745",
        "diff_url": "https://github.com/CyC2018/CS-Notes/pull/745.diff",
        "patch_url": "https://github.com/CyC2018/CS-Notes/pull/745.patch",
        "issue_url": "https://api.github.com/repos/CyC2018/CS-Notes/issues/745",
        "number": 745,
        "state": "open",
        "locked": false,
        "title": "Update 剑指 Offer 题解 - 3~9.md",
        "user": {
            "login": "HSUTZUHAN",
            "id": 15816679,
            "node_id": "MDQ6VXNlcjE1ODE2Njc5",
            "avatar_url": "https://avatars2.githubusercontent.com/u/15816679?v=4",
            "gravatar_id": "",
            "url": "https://api.github.com/users/HSUTZUHAN",
            "html_url": "https://github.com/HSUTZUHAN",
            "followers_url": "https://api.github.com/users/HSUTZUHAN/followers",
            "following_url": "https://api.github.com/users/HSUTZUHAN/following{/other_user}",
            "gists_url": "https://api.github.com/users/HSUTZUHAN/gists{/gist_id}",
            "starred_url": "https://api.github.com/users/HSUTZUHAN/starred{/owner}{/repo}",
            "subscriptions_url": "https://api.github.com/users/HSUTZUHAN/subscriptions",
            "organizations_url": "https://api.github.com/users/HSUTZUHAN/orgs",
            "repos_url": "https://api.github.com/users/HSUTZUHAN/repos",
            "events_url": "https://api.github.com/users/HSUTZUHAN/events{/privacy}",
            "received_events_url": "https://api.github.com/users/HSUTZUHAN/received_events",
            "type": "User",
            "site_admin": false
        },
        "body": "",
        "created_at": "2019-07-12T11:03:55Z",
        "updated_at": "2019-07-29T04:41:10Z",
        "closed_at": null,
        "merged_at": null,
        "merge_commit_sha": "61e074f4ce020d6aed45166b287ae874082b6ba3",
        "assignee": null,
        "assignees": [],
        "requested_reviewers": [],
        "requested_teams": [],
        "labels": [],
        "milestone": null,
        "commits_url": "https://api.github.com/repos/CyC2018/CS-Notes/pulls/745/commits",
        "review_comments_url": "https://api.github.com/repos/CyC2018/CS-Notes/pulls/745/comments",
        "review_comment_url": "https://api.github.com/repos/CyC2018/CS-Notes/pulls/comments{/number}",
        "comments_url": "https://api.github.com/repos/CyC2018/CS-Notes/issues/745/comments",
        "statuses_url": "https://api.github.com/repos/CyC2018/CS-Notes/statuses/2ac9cfc53468c2e6a8e99c5ac32de2760ecb140f",
        "head": {
            "label": "HSUTZUHAN:patch-2",
            "ref": "patch-2",
            "sha": "2ac9cfc53468c2e6a8e99c5ac32de2760ecb140f",
            "user": {
                "login": "HSUTZUHAN",
                "id": 15816679,
                "node_id": "MDQ6VXNlcjE1ODE2Njc5",
                "avatar_url": "https://avatars2.githubusercontent.com/u/15816679?v=4",
                "gravatar_id": "",
                "url": "https://api.github.com/users/HSUTZUHAN",
                "html_url": "https://github.com/HSUTZUHAN",
                "followers_url": "https://api.github.com/users/HSUTZUHAN/followers",
                "following_url": "https://api.github.com/users/HSUTZUHAN/following{/other_user}",
                "gists_url": "https://api.github.com/users/HSUTZUHAN/gists{/gist_id}",
                "starred_url": "https://api.github.com/users/HSUTZUHAN/starred{/owner}{/repo}",
                "subscriptions_url": "https://api.github.com/users/HSUTZUHAN/subscriptions",
                "organizations_url": "https://api.github.com/users/HSUTZUHAN/orgs",
                "repos_url": "https://api.github.com/users/HSUTZUHAN/repos",
                "events_url": "https://api.github.com/users/HSUTZUHAN/events{/privacy}",
                "received_events_url": "https://api.github.com/users/HSUTZUHAN/received_events",
                "type": "User",
                "site_admin": false
            },
            "repo": {
                "id": 196563753,
                "node_id": "MDEwOlJlcG9zaXRvcnkxOTY1NjM3NTM=",
                "name": "CS-Notes",
                "full_name": "HSUTZUHAN/CS-Notes",
                "private": false,
                "owner": {
                    "login": "HSUTZUHAN",
                    "id": 15816679,
                    "node_id": "MDQ6VXNlcjE1ODE2Njc5",
                    "avatar_url": "https://avatars2.githubusercontent.com/u/15816679?v=4",
                    "gravatar_id": "",
                    "url": "https://api.github.com/users/HSUTZUHAN",
                    "html_url": "https://github.com/HSUTZUHAN",
                    "followers_url": "https://api.github.com/users/HSUTZUHAN/followers",
                    "following_url": "https://api.github.com/users/HSUTZUHAN/following{/other_user}",
                    "gists_url": "https://api.github.com/users/HSUTZUHAN/gists{/gist_id}",
                    "starred_url": "https://api.github.com/users/HSUTZUHAN/starred{/owner}{/repo}",
                    "subscriptions_url": "https://api.github.com/users/HSUTZUHAN/subscriptions",
                    "organizations_url": "https://api.github.com/users/HSUTZUHAN/orgs",
                    "repos_url": "https://api.github.com/users/HSUTZUHAN/repos",
                    "events_url": "https://api.github.com/users/HSUTZUHAN/events{/privacy}",
                    "received_events_url": "https://api.github.com/users/HSUTZUHAN/received_events",
                    "type": "User",
                    "site_admin": false
                },
                "html_url": "https://github.com/HSUTZUHAN/CS-Notes",
                "description": ":books: Tech Interview Guide 技术面试必备基础知识、Leetcode 题解、Java、C++、Python、后端面试、操作系统、计算机网络、系统设计",
                "fork": true,
                "url": "https://api.github.com/repos/HSUTZUHAN/CS-Notes",
                "forks_url": "https://api.github.com/repos/HSUTZUHAN/CS-Notes/forks",
                "keys_url": "https://api.github.com/repos/HSUTZUHAN/CS-Notes/keys{/key_id}",
                "collaborators_url": "https://api.github.com/repos/HSUTZUHAN/CS-Notes/collaborators{/collaborator}",
                "teams_url": "https://api.github.com/repos/HSUTZUHAN/CS-Notes/teams",
                "hooks_url": "https://api.github.com/repos/HSUTZUHAN/CS-Notes/hooks",
                "issue_events_url": "https://api.github.com/repos/HSUTZUHAN/CS-Notes/issues/events{/number}",
                "events_url": "https://api.github.com/repos/HSUTZUHAN/CS-Notes/events",
                "assignees_url": "https://api.github.com/repos/HSUTZUHAN/CS-Notes/assignees{/user}",
                "branches_url": "https://api.github.com/repos/HSUTZUHAN/CS-Notes/branches{/branch}",
                "tags_url": "https://api.github.com/repos/HSUTZUHAN/CS-Notes/tags",
                "blobs_url": "https://api.github.com/repos/HSUTZUHAN/CS-Notes/git/blobs{/sha}",
                "git_tags_url": "https://api.github.com/repos/HSUTZUHAN/CS-Notes/git/tags{/sha}",
                "git_refs_url": "https://api.github.com/repos/HSUTZUHAN/CS-Notes/git/refs{/sha}",
                "trees_url": "https://api.github.com/repos/HSUTZUHAN/CS-Notes/git/trees{/sha}",
                "statuses_url": "https://api.github.com/repos/HSUTZUHAN/CS-Notes/statuses/{sha}",
                "languages_url": "https://api.github.com/repos/HSUTZUHAN/CS-Notes/languages",
                "stargazers_url": "https://api.github.com/repos/HSUTZUHAN/CS-Notes/stargazers",
                "contributors_url": "https://api.github.com/repos/HSUTZUHAN/CS-Notes/contributors",
                "subscribers_url": "https://api.github.com/repos/HSUTZUHAN/CS-Notes/subscribers",
                "subscription_url": "https://api.github.com/repos/HSUTZUHAN/CS-Notes/subscription",
                "commits_url": "https://api.github.com/repos/HSUTZUHAN/CS-Notes/commits{/sha}",
                "git_commits_url": "https://api.github.com/repos/HSUTZUHAN/CS-Notes/git/commits{/sha}",
                "comments_url": "https://api.github.com/repos/HSUTZUHAN/CS-Notes/comments{/number}",
                "issue_comment_url": "https://api.github.com/repos/HSUTZUHAN/CS-Notes/issues/comments{/number}",
                "contents_url": "https://api.github.com/repos/HSUTZUHAN/CS-Notes/contents/{+path}",
                "compare_url": "https://api.github.com/repos/HSUTZUHAN/CS-Notes/compare/{base}...{head}",
                "merges_url": "https://api.github.com/repos/HSUTZUHAN/CS-Notes/merges",
                "archive_url": "https://api.github.com/repos/HSUTZUHAN/CS-Notes/{archive_format}{/ref}",
                "downloads_url": "https://api.github.com/repos/HSUTZUHAN/CS-Notes/downloads",
                "issues_url": "https://api.github.com/repos/HSUTZUHAN/CS-Notes/issues{/number}",
                "pulls_url": "https://api.github.com/repos/HSUTZUHAN/CS-Notes/pulls{/number}",
                "milestones_url": "https://api.github.com/repos/HSUTZUHAN/CS-Notes/milestones{/number}",
                "notifications_url": "https://api.github.com/repos/HSUTZUHAN/CS-Notes/notifications{?since,all,participating}",
                "labels_url": "https://api.github.com/repos/HSUTZUHAN/CS-Notes/labels{/name}",
                "releases_url": "https://api.github.com/repos/HSUTZUHAN/CS-Notes/releases{/id}",
                "deployments_url": "https://api.github.com/repos/HSUTZUHAN/CS-Notes/deployments",
                "created_at": "2019-07-12T10:57:46Z",
                "updated_at": "2019-07-12T10:57:50Z",
                "pushed_at": "2019-07-12T11:02:37Z",
                "git_url": "git://github.com/HSUTZUHAN/CS-Notes.git",
                "ssh_url": "git@github.com:HSUTZUHAN/CS-Notes.git",
                "clone_url": "https://github.com/HSUTZUHAN/CS-Notes.git",
                "svn_url": "https://github.com/HSUTZUHAN/CS-Notes",
                "homepage": "https://cyc2018.github.io/CS-Notes",
                "size": 106713,
                "stargazers_count": 0,
                "watchers_count": 0,
                "language": "Java",
                "has_issues": false,
                "has_projects": true,
                "has_downloads": true,
                "has_wiki": true,
                "has_pages": false,
                "forks_count": 0,
                "mirror_url": null,
                "archived": false,
                "disabled": false,
                "open_issues_count": 0,
                "license": null,
                "forks": 0,
                "open_issues": 0,
                "watchers": 0,
                "default_branch": "master"
            }
        },
        "base": {
            "label": "CyC2018:master",
            "ref": "master",
            "sha": "a2220c04de982435181a7ee990d31a6adb248b9f",
            "user": {
                "login": "CyC2018",
                "id": 36260787,
                "node_id": "MDQ6VXNlcjM2MjYwNzg3",
                "avatar_url": "https://avatars3.githubusercontent.com/u/36260787?v=4",
                "gravatar_id": "",
                "url": "https://api.github.com/users/CyC2018",
                "html_url": "https://github.com/CyC2018",
                "followers_url": "https://api.github.com/users/CyC2018/followers",
                "following_url": "https://api.github.com/users/CyC2018/following{/other_user}",
                "gists_url": "https://api.github.com/users/CyC2018/gists{/gist_id}",
                "starred_url": "https://api.github.com/users/CyC2018/starred{/owner}{/repo}",
                "subscriptions_url": "https://api.github.com/users/CyC2018/subscriptions",
                "organizations_url": "https://api.github.com/users/CyC2018/orgs",
                "repos_url": "https://api.github.com/users/CyC2018/repos",
                "events_url": "https://api.github.com/users/CyC2018/events{/privacy}",
                "received_events_url": "https://api.github.com/users/CyC2018/received_events",
                "type": "User",
                "site_admin": false
            },
            "repo": {
                "id": 121395510,
                "node_id": "MDEwOlJlcG9zaXRvcnkxMjEzOTU1MTA=",
                "name": "CS-Notes",
                "full_name": "CyC2018/CS-Notes",
                "private": false,
                "owner": {
                    "login": "CyC2018",
                    "id": 36260787,
                    "node_id": "MDQ6VXNlcjM2MjYwNzg3",
                    "avatar_url": "https://avatars3.githubusercontent.com/u/36260787?v=4",
                    "gravatar_id": "",
                    "url": "https://api.github.com/users/CyC2018",
                    "html_url": "https://github.com/CyC2018",
                    "followers_url": "https://api.github.com/users/CyC2018/followers",
                    "following_url": "https://api.github.com/users/CyC2018/following{/other_user}",
                    "gists_url": "https://api.github.com/users/CyC2018/gists{/gist_id}",
                    "starred_url": "https://api.github.com/users/CyC2018/starred{/owner}{/repo}",
                    "subscriptions_url": "https://api.github.com/users/CyC2018/subscriptions",
                    "organizations_url": "https://api.github.com/users/CyC2018/orgs",
                    "repos_url": "https://api.github.com/users/CyC2018/repos",
                    "events_url": "https://api.github.com/users/CyC2018/events{/privacy}",
                    "received_events_url": "https://api.github.com/users/CyC2018/received_events",
                    "type": "User",
                    "site_admin": false
                },
                "html_url": "https://github.com/CyC2018/CS-Notes",
                "description": ":books: Tech Interview Guide 技术面试必备基础知识、Leetcode 题解、Java、C++、Python、后端面试、操作系统、计算机网络、系统设计",
                "fork": false,
                "url": "https://api.github.com/repos/CyC2018/CS-Notes",
                "forks_url": "https://api.github.com/repos/CyC2018/CS-Notes/forks",
                "keys_url": "https://api.github.com/repos/CyC2018/CS-Notes/keys{/key_id}",
                "collaborators_url": "https://api.github.com/repos/CyC2018/CS-Notes/collaborators{/collaborator}",
                "teams_url": "https://api.github.com/repos/CyC2018/CS-Notes/teams",
                "hooks_url": "https://api.github.com/repos/CyC2018/CS-Notes/hooks",
                "issue_events_url": "https://api.github.com/repos/CyC2018/CS-Notes/issues/events{/number}",
                "events_url": "https://api.github.com/repos/CyC2018/CS-Notes/events",
                "assignees_url": "https://api.github.com/repos/CyC2018/CS-Notes/assignees{/user}",
                "branches_url": "https://api.github.com/repos/CyC2018/CS-Notes/branches{/branch}",
                "tags_url": "https://api.github.com/repos/CyC2018/CS-Notes/tags",
                "blobs_url": "https://api.github.com/repos/CyC2018/CS-Notes/git/blobs{/sha}",
                "git_tags_url": "https://api.github.com/repos/CyC2018/CS-Notes/git/tags{/sha}",
                "git_refs_url": "https://api.github.com/repos/CyC2018/CS-Notes/git/refs{/sha}",
                "trees_url": "https://api.github.com/repos/CyC2018/CS-Notes/git/trees{/sha}",
                "statuses_url": "https://api.github.com/repos/CyC2018/CS-Notes/statuses/{sha}",
                "languages_url": "https://api.github.com/repos/CyC2018/CS-Notes/languages",
                "stargazers_url": "https://api.github.com/repos/CyC2018/CS-Notes/stargazers",
                "contributors_url": "https://api.github.com/repos/CyC2018/CS-Notes/contributors",
                "subscribers_url": "https://api.github.com/repos/CyC2018/CS-Notes/subscribers",
                "subscription_url": "https://api.github.com/repos/CyC2018/CS-Notes/subscription",
                "commits_url": "https://api.github.com/repos/CyC2018/CS-Notes/commits{/sha}",
                "git_commits_url": "https://api.github.com/repos/CyC2018/CS-Notes/git/commits{/sha}",
                "comments_url": "https://api.github.com/repos/CyC2018/CS-Notes/comments{/number}",
                "issue_comment_url": "https://api.github.com/repos/CyC2018/CS-Notes/issues/comments{/number}",
                "contents_url": "https://api.github.com/repos/CyC2018/CS-Notes/contents/{+path}",
                "compare_url": "https://api.github.com/repos/CyC2018/CS-Notes/compare/{base}...{head}",
                "merges_url": "https://api.github.com/repos/CyC2018/CS-Notes/merges",
                "archive_url": "https://api.github.com/repos/CyC2018/CS-Notes/{archive_format}{/ref}",
                "downloads_url": "https://api.github.com/repos/CyC2018/CS-Notes/downloads",
                "issues_url": "https://api.github.com/repos/CyC2018/CS-Notes/issues{/number}",
                "pulls_url": "https://api.github.com/repos/CyC2018/CS-Notes/pulls{/number}",
                "milestones_url": "https://api.github.com/repos/CyC2018/CS-Notes/milestones{/number}",
                "notifications_url": "https://api.github.com/repos/CyC2018/CS-Notes/notifications{?since,all,participating}",
                "labels_url": "https://api.github.com/repos/CyC2018/CS-Notes/labels{/name}",
                "releases_url": "https://api.github.com/repos/CyC2018/CS-Notes/releases{/id}",
                "deployments_url": "https://api.github.com/repos/CyC2018/CS-Notes/deployments",
                "created_at": "2018-02-13T14:56:24Z",
                "updated_at": "2019-08-11T17:16:23Z",
                "pushed_at": "2019-08-11T15:23:32Z",
                "git_url": "git://github.com/CyC2018/CS-Notes.git",
                "ssh_url": "git@github.com:CyC2018/CS-Notes.git",
                "clone_url": "https://github.com/CyC2018/CS-Notes.git",
                "svn_url": "https://github.com/CyC2018/CS-Notes",
                "homepage": "https://cyc2018.github.io/CS-Notes",
                "size": 106799,
                "stargazers_count": 73985,
                "watchers_count": 73985,
                "language": "Java",
                "has_issues": true,
                "has_projects": true,
                "has_downloads": true,
                "has_wiki": true,
                "has_pages": true,
                "forks_count": 23389,
                "mirror_url": null,
                "archived": false,
                "disabled": false,
                "open_issues_count": 16,
                "license": null,
                "forks": 23389,
                "open_issues": 16,
                "watchers": 73985,
                "default_branch": "master"
            }
        },
        "_links": {
            "self": {
                "href": "https://api.github.com/repos/CyC2018/CS-Notes/pulls/745"
            },
            "html": {
                "href": "https://github.com/CyC2018/CS-Notes/pull/745"
            },
            "issue": {
                "href": "https://api.github.com/repos/CyC2018/CS-Notes/issues/745"
            },
            "comments": {
                "href": "https://api.github.com/repos/CyC2018/CS-Notes/issues/745/comments"
            },
            "review_comments": {
                "href": "https://api.github.com/repos/CyC2018/CS-Notes/pulls/745/comments"
            },
            "review_comment": {
                "href": "https://api.github.com/repos/CyC2018/CS-Notes/pulls/comments{/number}"
            },
            "commits": {
                "href": "https://api.github.com/repos/CyC2018/CS-Notes/pulls/745/commits"
            },
            "statuses": {
                "href": "https://api.github.com/repos/CyC2018/CS-Notes/statuses/2ac9cfc53468c2e6a8e99c5ac32de2760ecb140f"
            }
        },
        "author_association": "NONE"
    },
    {
        "url": "https://api.github.com/repos/CyC2018/CS-Notes/pulls/735",
        "id": 293992017,
        "node_id": "MDExOlB1bGxSZXF1ZXN0MjkzOTkyMDE3",
        "html_url": "https://github.com/CyC2018/CS-Notes/pull/735",
        "diff_url": "https://github.com/CyC2018/CS-Notes/pull/735.diff",
        "patch_url": "https://github.com/CyC2018/CS-Notes/pull/735.patch",
        "issue_url": "https://api.github.com/repos/CyC2018/CS-Notes/issues/735",
        "number": 735,
        "state": "open",
        "locked": false,
        "title": "增加 HTTP/1.1 pipelining 缺陷描述 修正 QuickSort 中的小问题",
        "user": {
            "login": "imhuster",
            "id": 13541953,
            "node_id": "MDQ6VXNlcjEzNTQxOTUz",
            "avatar_url": "https://avatars0.githubusercontent.com/u/13541953?v=4",
            "gravatar_id": "",
            "url": "https://api.github.com/users/imhuster",
            "html_url": "https://github.com/imhuster",
            "followers_url": "https://api.github.com/users/imhuster/followers",
            "following_url": "https://api.github.com/users/imhuster/following{/other_user}",
            "gists_url": "https://api.github.com/users/imhuster/gists{/gist_id}",
            "starred_url": "https://api.github.com/users/imhuster/starred{/owner}{/repo}",
            "subscriptions_url": "https://api.github.com/users/imhuster/subscriptions",
            "organizations_url": "https://api.github.com/users/imhuster/orgs",
            "repos_url": "https://api.github.com/users/imhuster/repos",
            "events_url": "https://api.github.com/users/imhuster/events{/privacy}",
            "received_events_url": "https://api.github.com/users/imhuster/received_events",
            "type": "User",
            "site_admin": false
        },
        "body": "增加 HTTP/1.1 pipelining 缺陷描述 修正 QuickSort 中的小问题",
        "created_at": "2019-07-03T03:55:29Z",
        "updated_at": "2019-07-21T15:23:27Z",
        "closed_at": null,
        "merged_at": null,
        "merge_commit_sha": "49d3f73ab20534886d3cc9811a89a28eb388ac33",
        "assignee": null,
        "assignees": [],
        "requested_reviewers": [],
        "requested_teams": [],
        "labels": [],
        "milestone": null,
        "commits_url": "https://api.github.com/repos/CyC2018/CS-Notes/pulls/735/commits",
        "review_comments_url": "https://api.github.com/repos/CyC2018/CS-Notes/pulls/735/comments",
        "review_comment_url": "https://api.github.com/repos/CyC2018/CS-Notes/pulls/comments{/number}",
        "comments_url": "https://api.github.com/repos/CyC2018/CS-Notes/issues/735/comments",
        "statuses_url": "https://api.github.com/repos/CyC2018/CS-Notes/statuses/7ca2b079b48c3fa466c203d7170f35b5ee2e40c3",
        "head": {
            "label": "imhuster:master",
            "ref": "master",
            "sha": "7ca2b079b48c3fa466c203d7170f35b5ee2e40c3",
            "user": {
                "login": "imhuster",
                "id": 13541953,
                "node_id": "MDQ6VXNlcjEzNTQxOTUz",
                "avatar_url": "https://avatars0.githubusercontent.com/u/13541953?v=4",
                "gravatar_id": "",
                "url": "https://api.github.com/users/imhuster",
                "html_url": "https://github.com/imhuster",
                "followers_url": "https://api.github.com/users/imhuster/followers",
                "following_url": "https://api.github.com/users/imhuster/following{/other_user}",
                "gists_url": "https://api.github.com/users/imhuster/gists{/gist_id}",
                "starred_url": "https://api.github.com/users/imhuster/starred{/owner}{/repo}",
                "subscriptions_url": "https://api.github.com/users/imhuster/subscriptions",
                "organizations_url": "https://api.github.com/users/imhuster/orgs",
                "repos_url": "https://api.github.com/users/imhuster/repos",
                "events_url": "https://api.github.com/users/imhuster/events{/privacy}",
                "received_events_url": "https://api.github.com/users/imhuster/received_events",
                "type": "User",
                "site_admin": false
            },
            "repo": {
                "id": 173955456,
                "node_id": "MDEwOlJlcG9zaXRvcnkxNzM5NTU0NTY=",
                "name": "CS-Notes",
                "full_name": "imhuster/CS-Notes",
                "private": false,
                "owner": {
                    "login": "imhuster",
                    "id": 13541953,
                    "node_id": "MDQ6VXNlcjEzNTQxOTUz",
                    "avatar_url": "https://avatars0.githubusercontent.com/u/13541953?v=4",
                    "gravatar_id": "",
                    "url": "https://api.github.com/users/imhuster",
                    "html_url": "https://github.com/imhuster",
                    "followers_url": "https://api.github.com/users/imhuster/followers",
                    "following_url": "https://api.github.com/users/imhuster/following{/other_user}",
                    "gists_url": "https://api.github.com/users/imhuster/gists{/gist_id}",
                    "starred_url": "https://api.github.com/users/imhuster/starred{/owner}{/repo}",
                    "subscriptions_url": "https://api.github.com/users/imhuster/subscriptions",
                    "organizations_url": "https://api.github.com/users/imhuster/orgs",
                    "repos_url": "https://api.github.com/users/imhuster/repos",
                    "events_url": "https://api.github.com/users/imhuster/events{/privacy}",
                    "received_events_url": "https://api.github.com/users/imhuster/received_events",
                    "type": "User",
                    "site_admin": false
                },
                "html_url": "https://github.com/imhuster/CS-Notes",
                "description": "😋  技术面试必备基础知识",
                "fork": true,
                "url": "https://api.github.com/repos/imhuster/CS-Notes",
                "forks_url": "https://api.github.com/repos/imhuster/CS-Notes/forks",
                "keys_url": "https://api.github.com/repos/imhuster/CS-Notes/keys{/key_id}",
                "collaborators_url": "https://api.github.com/repos/imhuster/CS-Notes/collaborators{/collaborator}",
                "teams_url": "https://api.github.com/repos/imhuster/CS-Notes/teams",
                "hooks_url": "https://api.github.com/repos/imhuster/CS-Notes/hooks",
                "issue_events_url": "https://api.github.com/repos/imhuster/CS-Notes/issues/events{/number}",
                "events_url": "https://api.github.com/repos/imhuster/CS-Notes/events",
                "assignees_url": "https://api.github.com/repos/imhuster/CS-Notes/assignees{/user}",
                "branches_url": "https://api.github.com/repos/imhuster/CS-Notes/branches{/branch}",
                "tags_url": "https://api.github.com/repos/imhuster/CS-Notes/tags",
                "blobs_url": "https://api.github.com/repos/imhuster/CS-Notes/git/blobs{/sha}",
                "git_tags_url": "https://api.github.com/repos/imhuster/CS-Notes/git/tags{/sha}",
                "git_refs_url": "https://api.github.com/repos/imhuster/CS-Notes/git/refs{/sha}",
                "trees_url": "https://api.github.com/repos/imhuster/CS-Notes/git/trees{/sha}",
                "statuses_url": "https://api.github.com/repos/imhuster/CS-Notes/statuses/{sha}",
                "languages_url": "https://api.github.com/repos/imhuster/CS-Notes/languages",
                "stargazers_url": "https://api.github.com/repos/imhuster/CS-Notes/stargazers",
                "contributors_url": "https://api.github.com/repos/imhuster/CS-Notes/contributors",
                "subscribers_url": "https://api.github.com/repos/imhuster/CS-Notes/subscribers",
                "subscription_url": "https://api.github.com/repos/imhuster/CS-Notes/subscription",
                "commits_url": "https://api.github.com/repos/imhuster/CS-Notes/commits{/sha}",
                "git_commits_url": "https://api.github.com/repos/imhuster/CS-Notes/git/commits{/sha}",
                "comments_url": "https://api.github.com/repos/imhuster/CS-Notes/comments{/number}",
                "issue_comment_url": "https://api.github.com/repos/imhuster/CS-Notes/issues/comments{/number}",
                "contents_url": "https://api.github.com/repos/imhuster/CS-Notes/contents/{+path}",
                "compare_url": "https://api.github.com/repos/imhuster/CS-Notes/compare/{base}...{head}",
                "merges_url": "https://api.github.com/repos/imhuster/CS-Notes/merges",
                "archive_url": "https://api.github.com/repos/imhuster/CS-Notes/{archive_format}{/ref}",
                "downloads_url": "https://api.github.com/repos/imhuster/CS-Notes/downloads",
                "issues_url": "https://api.github.com/repos/imhuster/CS-Notes/issues{/number}",
                "pulls_url": "https://api.github.com/repos/imhuster/CS-Notes/pulls{/number}",
                "milestones_url": "https://api.github.com/repos/imhuster/CS-Notes/milestones{/number}",
                "notifications_url": "https://api.github.com/repos/imhuster/CS-Notes/notifications{?since,all,participating}",
                "labels_url": "https://api.github.com/repos/imhuster/CS-Notes/labels{/name}",
                "releases_url": "https://api.github.com/repos/imhuster/CS-Notes/releases{/id}",
                "deployments_url": "https://api.github.com/repos/imhuster/CS-Notes/deployments",
                "created_at": "2019-03-05T13:50:39Z",
                "updated_at": "2019-08-08T08:36:57Z",
                "pushed_at": "2019-07-03T03:53:12Z",
                "git_url": "git://github.com/imhuster/CS-Notes.git",
                "ssh_url": "git@github.com:imhuster/CS-Notes.git",
                "clone_url": "https://github.com/imhuster/CS-Notes.git",
                "svn_url": "https://github.com/imhuster/CS-Notes",
                "homepage": "https://cyc2018.github.io/CS-Notes",
                "size": 106706,
                "stargazers_count": 14,
                "watchers_count": 14,
                "language": "Java",
                "has_issues": false,
                "has_projects": true,
                "has_downloads": true,
                "has_wiki": true,
                "has_pages": false,
                "forks_count": 27,
                "mirror_url": null,
                "archived": false,
                "disabled": false,
                "open_issues_count": 0,
                "license": null,
                "forks": 27,
                "open_issues": 0,
                "watchers": 14,
                "default_branch": "master"
            }
        },
        "base": {
            "label": "CyC2018:master",
            "ref": "master",
            "sha": "a2220c04de982435181a7ee990d31a6adb248b9f",
            "user": {
                "login": "CyC2018",
                "id": 36260787,
                "node_id": "MDQ6VXNlcjM2MjYwNzg3",
                "avatar_url": "https://avatars3.githubusercontent.com/u/36260787?v=4",
                "gravatar_id": "",
                "url": "https://api.github.com/users/CyC2018",
                "html_url": "https://github.com/CyC2018",
                "followers_url": "https://api.github.com/users/CyC2018/followers",
                "following_url": "https://api.github.com/users/CyC2018/following{/other_user}",
                "gists_url": "https://api.github.com/users/CyC2018/gists{/gist_id}",
                "starred_url": "https://api.github.com/users/CyC2018/starred{/owner}{/repo}",
                "subscriptions_url": "https://api.github.com/users/CyC2018/subscriptions",
                "organizations_url": "https://api.github.com/users/CyC2018/orgs",
                "repos_url": "https://api.github.com/users/CyC2018/repos",
                "events_url": "https://api.github.com/users/CyC2018/events{/privacy}",
                "received_events_url": "https://api.github.com/users/CyC2018/received_events",
                "type": "User",
                "site_admin": false
            },
            "repo": {
                "id": 121395510,
                "node_id": "MDEwOlJlcG9zaXRvcnkxMjEzOTU1MTA=",
                "name": "CS-Notes",
                "full_name": "CyC2018/CS-Notes",
                "private": false,
                "owner": {
                    "login": "CyC2018",
                    "id": 36260787,
                    "node_id": "MDQ6VXNlcjM2MjYwNzg3",
                    "avatar_url": "https://avatars3.githubusercontent.com/u/36260787?v=4",
                    "gravatar_id": "",
                    "url": "https://api.github.com/users/CyC2018",
                    "html_url": "https://github.com/CyC2018",
                    "followers_url": "https://api.github.com/users/CyC2018/followers",
                    "following_url": "https://api.github.com/users/CyC2018/following{/other_user}",
                    "gists_url": "https://api.github.com/users/CyC2018/gists{/gist_id}",
                    "starred_url": "https://api.github.com/users/CyC2018/starred{/owner}{/repo}",
                    "subscriptions_url": "https://api.github.com/users/CyC2018/subscriptions",
                    "organizations_url": "https://api.github.com/users/CyC2018/orgs",
                    "repos_url": "https://api.github.com/users/CyC2018/repos",
                    "events_url": "https://api.github.com/users/CyC2018/events{/privacy}",
                    "received_events_url": "https://api.github.com/users/CyC2018/received_events",
                    "type": "User",
                    "site_admin": false
                },
                "html_url": "https://github.com/CyC2018/CS-Notes",
                "description": ":books: Tech Interview Guide 技术面试必备基础知识、Leetcode 题解、Java、C++、Python、后端面试、操作系统、计算机网络、系统设计",
                "fork": false,
                "url": "https://api.github.com/repos/CyC2018/CS-Notes",
                "forks_url": "https://api.github.com/repos/CyC2018/CS-Notes/forks",
                "keys_url": "https://api.github.com/repos/CyC2018/CS-Notes/keys{/key_id}",
                "collaborators_url": "https://api.github.com/repos/CyC2018/CS-Notes/collaborators{/collaborator}",
                "teams_url": "https://api.github.com/repos/CyC2018/CS-Notes/teams",
                "hooks_url": "https://api.github.com/repos/CyC2018/CS-Notes/hooks",
                "issue_events_url": "https://api.github.com/repos/CyC2018/CS-Notes/issues/events{/number}",
                "events_url": "https://api.github.com/repos/CyC2018/CS-Notes/events",
                "assignees_url": "https://api.github.com/repos/CyC2018/CS-Notes/assignees{/user}",
                "branches_url": "https://api.github.com/repos/CyC2018/CS-Notes/branches{/branch}",
                "tags_url": "https://api.github.com/repos/CyC2018/CS-Notes/tags",
                "blobs_url": "https://api.github.com/repos/CyC2018/CS-Notes/git/blobs{/sha}",
                "git_tags_url": "https://api.github.com/repos/CyC2018/CS-Notes/git/tags{/sha}",
                "git_refs_url": "https://api.github.com/repos/CyC2018/CS-Notes/git/refs{/sha}",
                "trees_url": "https://api.github.com/repos/CyC2018/CS-Notes/git/trees{/sha}",
                "statuses_url": "https://api.github.com/repos/CyC2018/CS-Notes/statuses/{sha}",
                "languages_url": "https://api.github.com/repos/CyC2018/CS-Notes/languages",
                "stargazers_url": "https://api.github.com/repos/CyC2018/CS-Notes/stargazers",
                "contributors_url": "https://api.github.com/repos/CyC2018/CS-Notes/contributors",
                "subscribers_url": "https://api.github.com/repos/CyC2018/CS-Notes/subscribers",
                "subscription_url": "https://api.github.com/repos/CyC2018/CS-Notes/subscription",
                "commits_url": "https://api.github.com/repos/CyC2018/CS-Notes/commits{/sha}",
                "git_commits_url": "https://api.github.com/repos/CyC2018/CS-Notes/git/commits{/sha}",
                "comments_url": "https://api.github.com/repos/CyC2018/CS-Notes/comments{/number}",
                "issue_comment_url": "https://api.github.com/repos/CyC2018/CS-Notes/issues/comments{/number}",
                "contents_url": "https://api.github.com/repos/CyC2018/CS-Notes/contents/{+path}",
                "compare_url": "https://api.github.com/repos/CyC2018/CS-Notes/compare/{base}...{head}",
                "merges_url": "https://api.github.com/repos/CyC2018/CS-Notes/merges",
                "archive_url": "https://api.github.com/repos/CyC2018/CS-Notes/{archive_format}{/ref}",
                "downloads_url": "https://api.github.com/repos/CyC2018/CS-Notes/downloads",
                "issues_url": "https://api.github.com/repos/CyC2018/CS-Notes/issues{/number}",
                "pulls_url": "https://api.github.com/repos/CyC2018/CS-Notes/pulls{/number}",
                "milestones_url": "https://api.github.com/repos/CyC2018/CS-Notes/milestones{/number}",
                "notifications_url": "https://api.github.com/repos/CyC2018/CS-Notes/notifications{?since,all,participating}",
                "labels_url": "https://api.github.com/repos/CyC2018/CS-Notes/labels{/name}",
                "releases_url": "https://api.github.com/repos/CyC2018/CS-Notes/releases{/id}",
                "deployments_url": "https://api.github.com/repos/CyC2018/CS-Notes/deployments",
                "created_at": "2018-02-13T14:56:24Z",
                "updated_at": "2019-08-11T17:16:23Z",
                "pushed_at": "2019-08-11T15:23:32Z",
                "git_url": "git://github.com/CyC2018/CS-Notes.git",
                "ssh_url": "git@github.com:CyC2018/CS-Notes.git",
                "clone_url": "https://github.com/CyC2018/CS-Notes.git",
                "svn_url": "https://github.com/CyC2018/CS-Notes",
                "homepage": "https://cyc2018.github.io/CS-Notes",
                "size": 106799,
                "stargazers_count": 73985,
                "watchers_count": 73985,
                "language": "Java",
                "has_issues": true,
                "has_projects": true,
                "has_downloads": true,
                "has_wiki": true,
                "has_pages": true,
                "forks_count": 23389,
                "mirror_url": null,
                "archived": false,
                "disabled": false,
                "open_issues_count": 16,
                "license": null,
                "forks": 23389,
                "open_issues": 16,
                "watchers": 73985,
                "default_branch": "master"
            }
        },
        "_links": {
            "self": {
                "href": "https://api.github.com/repos/CyC2018/CS-Notes/pulls/735"
            },
            "html": {
                "href": "https://github.com/CyC2018/CS-Notes/pull/735"
            },
            "issue": {
                "href": "https://api.github.com/repos/CyC2018/CS-Notes/issues/735"
            },
            "comments": {
                "href": "https://api.github.com/repos/CyC2018/CS-Notes/issues/735/comments"
            },
            "review_comments": {
                "href": "https://api.github.com/repos/CyC2018/CS-Notes/pulls/735/comments"
            },
            "review_comment": {
                "href": "https://api.github.com/repos/CyC2018/CS-Notes/pulls/comments{/number}"
            },
            "commits": {
                "href": "https://api.github.com/repos/CyC2018/CS-Notes/pulls/735/commits"
            },
            "statuses": {
                "href": "https://api.github.com/repos/CyC2018/CS-Notes/statuses/7ca2b079b48c3fa466c203d7170f35b5ee2e40c3"
            }
        },
        "author_association": "CONTRIBUTOR"
    },
    {
        "url": "https://api.github.com/repos/CyC2018/CS-Notes/pulls/734",
        "id": 293013762,
        "node_id": "MDExOlB1bGxSZXF1ZXN0MjkzMDEzNzYy",
        "html_url": "https://github.com/CyC2018/CS-Notes/pull/734",
        "diff_url": "https://github.com/CyC2018/CS-Notes/pull/734.diff",
        "patch_url": "https://github.com/CyC2018/CS-Notes/pull/734.patch",
        "issue_url": "https://api.github.com/repos/CyC2018/CS-Notes/issues/734",
        "number": 734,
        "state": "open",
        "locked": false,
        "title": "为leetcode392题增加后续挑战题解",
        "user": {
            "login": "hanggegreat",
            "id": 23375548,
            "node_id": "MDQ6VXNlcjIzMzc1NTQ4",
            "avatar_url": "https://avatars0.githubusercontent.com/u/23375548?v=4",
            "gravatar_id": "",
            "url": "https://api.github.com/users/hanggegreat",
            "html_url": "https://github.com/hanggegreat",
            "followers_url": "https://api.github.com/users/hanggegreat/followers",
            "following_url": "https://api.github.com/users/hanggegreat/following{/other_user}",
            "gists_url": "https://api.github.com/users/hanggegreat/gists{/gist_id}",
            "starred_url": "https://api.github.com/users/hanggegreat/starred{/owner}{/repo}",
            "subscriptions_url": "https://api.github.com/users/hanggegreat/subscriptions",
            "organizations_url": "https://api.github.com/users/hanggegreat/orgs",
            "repos_url": "https://api.github.com/users/hanggegreat/repos",
            "events_url": "https://api.github.com/users/hanggegreat/events{/privacy}",
            "received_events_url": "https://api.github.com/users/hanggegreat/received_events",
            "type": "User",
            "site_admin": false
        },
        "body": "",
        "created_at": "2019-06-29T04:48:33Z",
        "updated_at": "2019-06-29T04:48:33Z",
        "closed_at": null,
        "merged_at": null,
        "merge_commit_sha": "74f87cd57d450f512544ec310fc49d9d455af7be",
        "assignee": null,
        "assignees": [],
        "requested_reviewers": [],
        "requested_teams": [],
        "labels": [],
        "milestone": null,
        "commits_url": "https://api.github.com/repos/CyC2018/CS-Notes/pulls/734/commits",
        "review_comments_url": "https://api.github.com/repos/CyC2018/CS-Notes/pulls/734/comments",
        "review_comment_url": "https://api.github.com/repos/CyC2018/CS-Notes/pulls/comments{/number}",
        "comments_url": "https://api.github.com/repos/CyC2018/CS-Notes/issues/734/comments",
        "statuses_url": "https://api.github.com/repos/CyC2018/CS-Notes/statuses/25b4dfdc709753c2efc5515c488eda6e21a6f806",
        "head": {
            "label": "hanggegreat:master",
            "ref": "master",
            "sha": "25b4dfdc709753c2efc5515c488eda6e21a6f806",
            "user": {
                "login": "hanggegreat",
                "id": 23375548,
                "node_id": "MDQ6VXNlcjIzMzc1NTQ4",
                "avatar_url": "https://avatars0.githubusercontent.com/u/23375548?v=4",
                "gravatar_id": "",
                "url": "https://api.github.com/users/hanggegreat",
                "html_url": "https://github.com/hanggegreat",
                "followers_url": "https://api.github.com/users/hanggegreat/followers",
                "following_url": "https://api.github.com/users/hanggegreat/following{/other_user}",
                "gists_url": "https://api.github.com/users/hanggegreat/gists{/gist_id}",
                "starred_url": "https://api.github.com/users/hanggegreat/starred{/owner}{/repo}",
                "subscriptions_url": "https://api.github.com/users/hanggegreat/subscriptions",
                "organizations_url": "https://api.github.com/users/hanggegreat/orgs",
                "repos_url": "https://api.github.com/users/hanggegreat/repos",
                "events_url": "https://api.github.com/users/hanggegreat/events{/privacy}",
                "received_events_url": "https://api.github.com/users/hanggegreat/received_events",
                "type": "User",
                "site_admin": false
            },
            "repo": {
                "id": 166154799,
                "node_id": "MDEwOlJlcG9zaXRvcnkxNjYxNTQ3OTk=",
                "name": "CS-Notes",
                "full_name": "hanggegreat/CS-Notes",
                "private": false,
                "owner": {
                    "login": "hanggegreat",
                    "id": 23375548,
                    "node_id": "MDQ6VXNlcjIzMzc1NTQ4",
                    "avatar_url": "https://avatars0.githubusercontent.com/u/23375548?v=4",
                    "gravatar_id": "",
                    "url": "https://api.github.com/users/hanggegreat",
                    "html_url": "https://github.com/hanggegreat",
                    "followers_url": "https://api.github.com/users/hanggegreat/followers",
                    "following_url": "https://api.github.com/users/hanggegreat/following{/other_user}",
                    "gists_url": "https://api.github.com/users/hanggegreat/gists{/gist_id}",
                    "starred_url": "https://api.github.com/users/hanggegreat/starred{/owner}{/repo}",
                    "subscriptions_url": "https://api.github.com/users/hanggegreat/subscriptions",
                    "organizations_url": "https://api.github.com/users/hanggegreat/orgs",
                    "repos_url": "https://api.github.com/users/hanggegreat/repos",
                    "events_url": "https://api.github.com/users/hanggegreat/events{/privacy}",
                    "received_events_url": "https://api.github.com/users/hanggegreat/received_events",
                    "type": "User",
                    "site_admin": false
                },
                "html_url": "https://github.com/hanggegreat/CS-Notes",
                "description": ":books: 面试必备基础知识",
                "fork": true,
                "url": "https://api.github.com/repos/hanggegreat/CS-Notes",
                "forks_url": "https://api.github.com/repos/hanggegreat/CS-Notes/forks",
                "keys_url": "https://api.github.com/repos/hanggegreat/CS-Notes/keys{/key_id}",
                "collaborators_url": "https://api.github.com/repos/hanggegreat/CS-Notes/collaborators{/collaborator}",
                "teams_url": "https://api.github.com/repos/hanggegreat/CS-Notes/teams",
                "hooks_url": "https://api.github.com/repos/hanggegreat/CS-Notes/hooks",
                "issue_events_url": "https://api.github.com/repos/hanggegreat/CS-Notes/issues/events{/number}",
                "events_url": "https://api.github.com/repos/hanggegreat/CS-Notes/events",
                "assignees_url": "https://api.github.com/repos/hanggegreat/CS-Notes/assignees{/user}",
                "branches_url": "https://api.github.com/repos/hanggegreat/CS-Notes/branches{/branch}",
                "tags_url": "https://api.github.com/repos/hanggegreat/CS-Notes/tags",
                "blobs_url": "https://api.github.com/repos/hanggegreat/CS-Notes/git/blobs{/sha}",
                "git_tags_url": "https://api.github.com/repos/hanggegreat/CS-Notes/git/tags{/sha}",
                "git_refs_url": "https://api.github.com/repos/hanggegreat/CS-Notes/git/refs{/sha}",
                "trees_url": "https://api.github.com/repos/hanggegreat/CS-Notes/git/trees{/sha}",
                "statuses_url": "https://api.github.com/repos/hanggegreat/CS-Notes/statuses/{sha}",
                "languages_url": "https://api.github.com/repos/hanggegreat/CS-Notes/languages",
                "stargazers_url": "https://api.github.com/repos/hanggegreat/CS-Notes/stargazers",
                "contributors_url": "https://api.github.com/repos/hanggegreat/CS-Notes/contributors",
                "subscribers_url": "https://api.github.com/repos/hanggegreat/CS-Notes/subscribers",
                "subscription_url": "https://api.github.com/repos/hanggegreat/CS-Notes/subscription",
                "commits_url": "https://api.github.com/repos/hanggegreat/CS-Notes/commits{/sha}",
                "git_commits_url": "https://api.github.com/repos/hanggegreat/CS-Notes/git/commits{/sha}",
                "comments_url": "https://api.github.com/repos/hanggegreat/CS-Notes/comments{/number}",
                "issue_comment_url": "https://api.github.com/repos/hanggegreat/CS-Notes/issues/comments{/number}",
                "contents_url": "https://api.github.com/repos/hanggegreat/CS-Notes/contents/{+path}",
                "compare_url": "https://api.github.com/repos/hanggegreat/CS-Notes/compare/{base}...{head}",
                "merges_url": "https://api.github.com/repos/hanggegreat/CS-Notes/merges",
                "archive_url": "https://api.github.com/repos/hanggegreat/CS-Notes/{archive_format}{/ref}",
                "downloads_url": "https://api.github.com/repos/hanggegreat/CS-Notes/downloads",
                "issues_url": "https://api.github.com/repos/hanggegreat/CS-Notes/issues{/number}",
                "pulls_url": "https://api.github.com/repos/hanggegreat/CS-Notes/pulls{/number}",
                "milestones_url": "https://api.github.com/repos/hanggegreat/CS-Notes/milestones{/number}",
                "notifications_url": "https://api.github.com/repos/hanggegreat/CS-Notes/notifications{?since,all,participating}",
                "labels_url": "https://api.github.com/repos/hanggegreat/CS-Notes/labels{/name}",
                "releases_url": "https://api.github.com/repos/hanggegreat/CS-Notes/releases{/id}",
                "deployments_url": "https://api.github.com/repos/hanggegreat/CS-Notes/deployments",
                "created_at": "2019-01-17T03:35:14Z",
                "updated_at": "2019-06-29T04:43:15Z",
                "pushed_at": "2019-08-10T14:25:48Z",
                "git_url": "git://github.com/hanggegreat/CS-Notes.git",
                "ssh_url": "git@github.com:hanggegreat/CS-Notes.git",
                "clone_url": "https://github.com/hanggegreat/CS-Notes.git",
                "svn_url": "https://github.com/hanggegreat/CS-Notes",
                "homepage": "https://cyc2018.github.io/CS-Notes",
                "size": 106797,
                "stargazers_count": 2,
                "watchers_count": 2,
                "language": "Java",
                "has_issues": false,
                "has_projects": true,
                "has_downloads": true,
                "has_wiki": true,
                "has_pages": false,
                "forks_count": 0,
                "mirror_url": null,
                "archived": false,
                "disabled": false,
                "open_issues_count": 0,
                "license": null,
                "forks": 0,
                "open_issues": 0,
                "watchers": 2,
                "default_branch": "master"
            }
        },
        "base": {
            "label": "CyC2018:master",
            "ref": "master",
            "sha": "a2220c04de982435181a7ee990d31a6adb248b9f",
            "user": {
                "login": "CyC2018",
                "id": 36260787,
                "node_id": "MDQ6VXNlcjM2MjYwNzg3",
                "avatar_url": "https://avatars3.githubusercontent.com/u/36260787?v=4",
                "gravatar_id": "",
                "url": "https://api.github.com/users/CyC2018",
                "html_url": "https://github.com/CyC2018",
                "followers_url": "https://api.github.com/users/CyC2018/followers",
                "following_url": "https://api.github.com/users/CyC2018/following{/other_user}",
                "gists_url": "https://api.github.com/users/CyC2018/gists{/gist_id}",
                "starred_url": "https://api.github.com/users/CyC2018/starred{/owner}{/repo}",
                "subscriptions_url": "https://api.github.com/users/CyC2018/subscriptions",
                "organizations_url": "https://api.github.com/users/CyC2018/orgs",
                "repos_url": "https://api.github.com/users/CyC2018/repos",
                "events_url": "https://api.github.com/users/CyC2018/events{/privacy}",
                "received_events_url": "https://api.github.com/users/CyC2018/received_events",
                "type": "User",
                "site_admin": false
            },
            "repo": {
                "id": 121395510,
                "node_id": "MDEwOlJlcG9zaXRvcnkxMjEzOTU1MTA=",
                "name": "CS-Notes",
                "full_name": "CyC2018/CS-Notes",
                "private": false,
                "owner": {
                    "login": "CyC2018",
                    "id": 36260787,
                    "node_id": "MDQ6VXNlcjM2MjYwNzg3",
                    "avatar_url": "https://avatars3.githubusercontent.com/u/36260787?v=4",
                    "gravatar_id": "",
                    "url": "https://api.github.com/users/CyC2018",
                    "html_url": "https://github.com/CyC2018",
                    "followers_url": "https://api.github.com/users/CyC2018/followers",
                    "following_url": "https://api.github.com/users/CyC2018/following{/other_user}",
                    "gists_url": "https://api.github.com/users/CyC2018/gists{/gist_id}",
                    "starred_url": "https://api.github.com/users/CyC2018/starred{/owner}{/repo}",
                    "subscriptions_url": "https://api.github.com/users/CyC2018/subscriptions",
                    "organizations_url": "https://api.github.com/users/CyC2018/orgs",
                    "repos_url": "https://api.github.com/users/CyC2018/repos",
                    "events_url": "https://api.github.com/users/CyC2018/events{/privacy}",
                    "received_events_url": "https://api.github.com/users/CyC2018/received_events",
                    "type": "User",
                    "site_admin": false
                },
                "html_url": "https://github.com/CyC2018/CS-Notes",
                "description": ":books: Tech Interview Guide 技术面试必备基础知识、Leetcode 题解、Java、C++、Python、后端面试、操作系统、计算机网络、系统设计",
                "fork": false,
                "url": "https://api.github.com/repos/CyC2018/CS-Notes",
                "forks_url": "https://api.github.com/repos/CyC2018/CS-Notes/forks",
                "keys_url": "https://api.github.com/repos/CyC2018/CS-Notes/keys{/key_id}",
                "collaborators_url": "https://api.github.com/repos/CyC2018/CS-Notes/collaborators{/collaborator}",
                "teams_url": "https://api.github.com/repos/CyC2018/CS-Notes/teams",
                "hooks_url": "https://api.github.com/repos/CyC2018/CS-Notes/hooks",
                "issue_events_url": "https://api.github.com/repos/CyC2018/CS-Notes/issues/events{/number}",
                "events_url": "https://api.github.com/repos/CyC2018/CS-Notes/events",
                "assignees_url": "https://api.github.com/repos/CyC2018/CS-Notes/assignees{/user}",
                "branches_url": "https://api.github.com/repos/CyC2018/CS-Notes/branches{/branch}",
                "tags_url": "https://api.github.com/repos/CyC2018/CS-Notes/tags",
                "blobs_url": "https://api.github.com/repos/CyC2018/CS-Notes/git/blobs{/sha}",
                "git_tags_url": "https://api.github.com/repos/CyC2018/CS-Notes/git/tags{/sha}",
                "git_refs_url": "https://api.github.com/repos/CyC2018/CS-Notes/git/refs{/sha}",
                "trees_url": "https://api.github.com/repos/CyC2018/CS-Notes/git/trees{/sha}",
                "statuses_url": "https://api.github.com/repos/CyC2018/CS-Notes/statuses/{sha}",
                "languages_url": "https://api.github.com/repos/CyC2018/CS-Notes/languages",
                "stargazers_url": "https://api.github.com/repos/CyC2018/CS-Notes/stargazers",
                "contributors_url": "https://api.github.com/repos/CyC2018/CS-Notes/contributors",
                "subscribers_url": "https://api.github.com/repos/CyC2018/CS-Notes/subscribers",
                "subscription_url": "https://api.github.com/repos/CyC2018/CS-Notes/subscription",
                "commits_url": "https://api.github.com/repos/CyC2018/CS-Notes/commits{/sha}",
                "git_commits_url": "https://api.github.com/repos/CyC2018/CS-Notes/git/commits{/sha}",
                "comments_url": "https://api.github.com/repos/CyC2018/CS-Notes/comments{/number}",
                "issue_comment_url": "https://api.github.com/repos/CyC2018/CS-Notes/issues/comments{/number}",
                "contents_url": "https://api.github.com/repos/CyC2018/CS-Notes/contents/{+path}",
                "compare_url": "https://api.github.com/repos/CyC2018/CS-Notes/compare/{base}...{head}",
                "merges_url": "https://api.github.com/repos/CyC2018/CS-Notes/merges",
                "archive_url": "https://api.github.com/repos/CyC2018/CS-Notes/{archive_format}{/ref}",
                "downloads_url": "https://api.github.com/repos/CyC2018/CS-Notes/downloads",
                "issues_url": "https://api.github.com/repos/CyC2018/CS-Notes/issues{/number}",
                "pulls_url": "https://api.github.com/repos/CyC2018/CS-Notes/pulls{/number}",
                "milestones_url": "https://api.github.com/repos/CyC2018/CS-Notes/milestones{/number}",
                "notifications_url": "https://api.github.com/repos/CyC2018/CS-Notes/notifications{?since,all,participating}",
                "labels_url": "https://api.github.com/repos/CyC2018/CS-Notes/labels{/name}",
                "releases_url": "https://api.github.com/repos/CyC2018/CS-Notes/releases{/id}",
                "deployments_url": "https://api.github.com/repos/CyC2018/CS-Notes/deployments",
                "created_at": "2018-02-13T14:56:24Z",
                "updated_at": "2019-08-11T17:16:23Z",
                "pushed_at": "2019-08-11T15:23:32Z",
                "git_url": "git://github.com/CyC2018/CS-Notes.git",
                "ssh_url": "git@github.com:CyC2018/CS-Notes.git",
                "clone_url": "https://github.com/CyC2018/CS-Notes.git",
                "svn_url": "https://github.com/CyC2018/CS-Notes",
                "homepage": "https://cyc2018.github.io/CS-Notes",
                "size": 106799,
                "stargazers_count": 73985,
                "watchers_count": 73985,
                "language": "Java",
                "has_issues": true,
                "has_projects": true,
                "has_downloads": true,
                "has_wiki": true,
                "has_pages": true,
                "forks_count": 23389,
                "mirror_url": null,
                "archived": false,
                "disabled": false,
                "open_issues_count": 16,
                "license": null,
                "forks": 23389,
                "open_issues": 16,
                "watchers": 73985,
                "default_branch": "master"
            }
        },
        "_links": {
            "self": {
                "href": "https://api.github.com/repos/CyC2018/CS-Notes/pulls/734"
            },
            "html": {
                "href": "https://github.com/CyC2018/CS-Notes/pull/734"
            },
            "issue": {
                "href": "https://api.github.com/repos/CyC2018/CS-Notes/issues/734"
            },
            "comments": {
                "href": "https://api.github.com/repos/CyC2018/CS-Notes/issues/734/comments"
            },
            "review_comments": {
                "href": "https://api.github.com/repos/CyC2018/CS-Notes/pulls/734/comments"
            },
            "review_comment": {
                "href": "https://api.github.com/repos/CyC2018/CS-Notes/pulls/comments{/number}"
            },
            "commits": {
                "href": "https://api.github.com/repos/CyC2018/CS-Notes/pulls/734/commits"
            },
            "statuses": {
                "href": "https://api.github.com/repos/CyC2018/CS-Notes/statuses/25b4dfdc709753c2efc5515c488eda6e21a6f806"
            }
        },
        "author_association": "NONE"
    }
]
